clarke_error_grid/__init__.py
clarke_error_grid/core.py
clarke_error_grid-0.1.1.dist-info/METADATA
clarke_error_grid-0.1.1.dist-info/WHEEL
clarke_error_grid-0.1.1.dist-info/top_level.txt
clarke_error_grid-0.1.1.dist-info/RECORD
