Metadata-Version: 2.4
Name: clarke-error-grid
Version: 0.1.1
Summary: Clarke Error Grid analysis and plotly plot for glucose prediction models
Author: Saurabh Barthwal
License: MIT
Project-URL: Homepage, https://github.com/barthwalsaurabh0/clarke-error-grid
Classifier: Programming Language :: Python :: 3
Classifier: License :: OSI Approved :: MIT License
Classifier: Intended Audience :: Science/Research
Classifier: Topic :: Scientific/Engineering :: Medical Science Apps.
Requires-Python: >=3.8
Requires-Dist: plotly>=5.0
